{
    "@class": "com.kony.gen.viz.model.component.KVizListBox",
    "DNDConfig": null,
    "_height_": {
        "type": "string",
        "value": "30dp"
    },
    "_left_": {
        "type": "string",
        "value": "5dp"
    },
    "_margin_": [
        0,
        0,
        0,
        0
    ],
    "_padding_": [
        1,
        0,
        1,
        0
    ],
    "_placeholder_": "Please Select",
    "_skin_": "scf77f7a2da841c38d92d5d939e127aa",
    "_width_": {
        "type": "string",
        "value": "95dp"
    },
    "android": {
        "psp": {
            "applySkinsToPopup": false
        }
    },
    "canUpdateUI": true,
    "centery": {
        "type": "string",
        "value": "50%"
    },
    "containerweight": 100,
    "contentalignment": 4,
    "dropdownimage": "down_arrow.png",
    "focusskin": "scf77f7a2da841c38d92d5d939e127aa",
    "groupcells": false,
    "id": "listBoxGroup",
    "info": null,
    "inputAccessoryViewType": 1,
    "iphone": {
        "psp": {
            "inputAccessoryViewType": 2
        }
    },
    "iscustomlayout": false,
    "isvisible": true,
    "kuid": "i1b6b4cbfe6e40de8d37088270ee6a2a",
    "masterdata": [
        [
            "key1",
            "Math"
        ],
        [
            "key2",
            "History"
        ]
    ],
    "name": "kony.ui.ListBox",
    "paddinginpixel": false,
    "parent": "flxChangeGroup",
    "pf": "frmDetails",
    "retaincontentalignment": false,
    "retainflexpositionproperties": false,
    "selectedkeys": null,
    "selectedkeyvalue": null,
    "selectedkeyvalues": null,
    "size": 18,
    "viewconfig": {
        "toggleViewConfig": {
            "viewStyle": 0
        }
    },
    "viewtype": 0,
    "wType": "ListBox",
    "zindex": 1
}